ku_of_fuzzy/__init__.py
ku_of_fuzzy/fuzzy_calculate.py
ku_of_fuzzy-0.1.6.dist-info/LICENSE
ku_of_fuzzy-0.1.6.dist-info/METADATA
ku_of_fuzzy-0.1.6.dist-info/WHEEL
ku_of_fuzzy-0.1.6.dist-info/top_level.txt
ku_of_fuzzy-0.1.6.dist-info/RECORD
