Metadata-Version: 2.1
Name: ku_of_fuzzy
Version: 0.1.6
Summary: 用于模糊数学计算的Python库
Home-page: https://github.com/YueorLekai/ku_of_fuzzy
Author: Yuekai
Author-email: 1977269004@qq.com
Classifier: Programming Language :: Python :: 3
Classifier: License :: OSI Approved :: MIT License
Classifier: Operating System :: OS Independent
Requires-Python: >=3.6
License-File: LICENSE
Requires-Dist: pandas >=2.2.1
Requires-Dist: numpy >=1.26.4
Requires-Dist: scipy >=1.13.0
Requires-Dist: matplotlib >=3.8.3
